simple_term_menu.py
simple_term_menu-1.6.5.dist-info/LICENSE
simple_term_menu-1.6.5.dist-info/METADATA
simple_term_menu-1.6.5.dist-info/WHEEL
simple_term_menu-1.6.5.dist-info/entry_points.txt
simple_term_menu-1.6.5.dist-info/top_level.txt
simple_term_menu-1.6.5.dist-info/RECORD
