Metadata-Version: 2.1
Name: simple-term-menu
Version: 1.6.5
Summary: A Python package which creates simple interactive menus on the command line.
Home-page: https://github.com/IngoMeyer441/simple-term-menu
Author: Ingo Meyer
Author-email: i.meyer@fz-juelich.de
License: MIT
Keywords: terminal,menu,choice
Classifier: Development Status :: 5 - Production/Stable
Classifier: Environment :: Console
Classifier: License :: OSI Approved :: MIT License
Classifier: Operating System :: MacOS
Classifier: Operating System :: POSIX :: Linux
Classifier: Programming Language :: Python
Classifier: Programming Language :: Python :: 3
Classifier: Programming Language :: Python :: 3.3
Classifier: Programming Language :: Python :: 3.4
Classifier: Programming Language :: Python :: 3.5
Classifier: Programming Language :: Python :: 3.6
Classifier: Programming Language :: Python :: 3.7
Classifier: Programming Language :: Python :: 3.8
Classifier: Programming Language :: Python :: 3 :: Only
Classifier: Topic :: Terminals
Classifier: Topic :: Utilities
Requires-Python: ~=3.5
License-File: LICENSE
